robovision/__init__.py
robovision/core.py
robovision/deck.py
robovision/overlay.py
robovision/preprocessor.py
robovision/target.py
robovision/utils.py
robovision/video_stream.py
robovision/video/__init__.py
robovision/video/abstract_cam.py
robovision/video/ipcam.py
robovision/video/jetsoncam.py
robovision/video/picam.py
robovision/video/webcam.py
robovision-0.1.4.dist-info/DESCRIPTION.rst
robovision-0.1.4.dist-info/METADATA
robovision-0.1.4.dist-info/RECORD
robovision-0.1.4.dist-info/WHEEL
robovision-0.1.4.dist-info/metadata.json
robovision-0.1.4.dist-info/top_level.txt
