Metadata-Version: 2.0
Name: robovision
Version: 0.1.4
Summary: Image processing functions useful for FRC robotics teams (and other purposes)
Home-page: https://github.com/skypanther/robovision
Author: Tim Poulsen
Author-email: tim@skypanther.com
License: MIT
Download-URL: https://github.com/skypanther/robovision/tarball/0.1.4
Keywords: robot,first robotics,frc,computer vision,image processing,opencv
Platform: UNKNOWN
Classifier: Development Status :: 3 - Alpha
Classifier: Intended Audience :: Developers
Classifier: Programming Language :: Python :: 3
